[{"id": 0, "name": 0, "module": [{"id": 0, "name": "0_0", "RAM": 5, "type": "MODULE"}, {"id": 1, "name": "0_1", "RAM": 5, "type": "MODULE"}, {"id": 2, "name": "0_2", "RAM": 2, "type": "MODULE"}, {"id": 3, "name": "0_3", "RAM": 2, "type": "MODULE"}], "message": [{"id": 0, "name": "M.USER.APP.0", "s": "None", "d": "0_0", "instructions": 48960, "bytes": 3127609}, {"id": 1, "name": "0_(0-1)", "s": "0_0", "d": "0_1", "instructions": 57487, "bytes": 3019574}, {"id": 2, "name": "0_(1-2)", "s": "0_1", "d": "0_2", "instructions": 57797, "bytes": 2972186}, {"id": 3, "name": "0_(2-3)", "s": "0_2", "d": "0_3", "instructions": 41126, "bytes": 4253833}], "transmission": [{"module": "0_0", "message_in": "M.USER.APP.0", "message_out": "0_(0-1)"}, {"module": "0_1", "message_in": "0_(0-1)", "message_out": "0_(1-2)"}, {"module": "0_2", "message_in": "0_(1-2)", "message_out": "0_(2-3)"}, {"module": "0_3", "message_in": "0_(2-3)"}]}, {"id": 1, "name": 1, "module": [{"id": 0, "name": "1_0", "RAM": 2, "type": "MODULE"}, {"id": 1, "name": "1_1", "RAM": 5, "type": "MODULE"}], "message": [{"id": 0, "name": "M.USER.APP.1", "s": "None", "d": "1_0", "instructions": 52603, "bytes": 3856421}, {"id": 1, "name": "1_(0-1)", "s": "1_0", "d": "1_1", "instructions": 55467, "bytes": 4477178}], "transmission": [{"module": "1_0", "message_in": "M.USER.APP.1", "message_out": "1_(0-1)"}, {"module": "1_1", "message_in": "1_(0-1)"}]}, {"id": 2, "name": 2, "module": [{"id": 0, "name": "2_0", "RAM": 2, "type": "MODULE"}, {"id": 1, "name": "2_1", "RAM": 5, "type": "MODULE"}, {"id": 2, "name": "2_2", "RAM": 4, "type": "MODULE"}, {"id": 3, "name": "2_3", "RAM": 2, "type": "MODULE"}], "message": [{"id": 0, "name": "M.USER.APP.2", "s": "None", "d": "2_0", "instructions": 58132, "bytes": 3838511}, {"id": 1, "name": "2_(0-1)", "s": "2_0", "d": "2_1", "instructions": 32486, "bytes": 3910679}, {"id": 2, "name": "2_(1-2)", "s": "2_1", "d": "2_2", "instructions": 25691, "bytes": 1708311}, {"id": 3, "name": "2_(2-3)", "s": "2_2", "d": "2_3", "instructions": 52066, "bytes": 2711816}], "transmission": [{"module": "2_0", "message_in": "M.USER.APP.2", "message_out": "2_(0-1)"}, {"module": "2_1", "message_in": "2_(0-1)", "message_out": "2_(1-2)"}, {"module": "2_2", "message_in": "2_(1-2)", "message_out": "2_(2-3)"}, {"module": "2_3", "message_in": "2_(2-3)"}]}, {"id": 3, "name": 3, "module": [{"id": 0, "name": "3_0", "RAM": 3, "type": "MODULE"}, {"id": 1, "name": "3_1", "RAM": 4, "type": "MODULE"}, {"id": 2, "name": "3_2", "RAM": 5, "type": "MODULE"}, {"id": 3, "name": "3_3", "RAM": 4, "type": "MODULE"}], "message": [{"id": 0, "name": "M.USER.APP.3", "s": "None", "d": "3_0", "instructions": 45482, "bytes": 4133966}, {"id": 1, "name": "3_(0-1)", "s": "3_0", "d": "3_1", "instructions": 30439, "bytes": 1857427}, {"id": 2, "name": "3_(1-2)", "s": "3_1", "d": "3_2", "instructions": 48844, "bytes": 3517644}, {"id": 3, "name": "3_(2-3)", "s": "3_2", "d": "3_3", "instructions": 54669, "bytes": 4174119}], "transmission": [{"module": "3_0", "message_in": "M.USER.APP.3", "message_out": "3_(0-1)"}, {"module": "3_1", "message_in": "3_(0-1)", "message_out": "3_(1-2)"}, {"module": "3_2", "message_in": "3_(1-2)", "message_out": "3_(2-3)"}, {"module": "3_3", "message_in": "3_(2-3)"}]}, {"id": 4, "name": 4, "module": [{"id": 0, "name": "4_0", "RAM": 2, "type": "MODULE"}, {"id": 1, "name": "4_1", "RAM": 5, "type": "MODULE"}], "message": [{"id": 0, "name": "M.USER.APP.4", "s": "None", "d": "4_0", "instructions": 50404, "bytes": 4393570}, {"id": 1, "name": "4_(0-1)", "s": "4_0", "d": "4_1", "instructions": 21511, "bytes": 2691895}], "transmission": [{"module": "4_0", "message_in": "M.USER.APP.4", "message_out": "4_(0-1)"}, {"module": "4_1", "message_in": "4_(0-1)"}]}, {"id": 5, "name": 5, "module": [{"id": 0, "name": "5_0", "RAM": 2, "type": "MODULE"}, {"id": 1, "name": "5_1", "RAM": 5, "type": "MODULE"}, {"id": 2, "name": "5_2", "RAM": 3, "type": "MODULE"}], "message": [{"id": 0, "name": "M.USER.APP.5", "s": "None", "d": "5_0", "instructions": 29660, "bytes": 2138029}, {"id": 1, "name": "5_(0-1)", "s": "5_0", "d": "5_1", "instructions": 26346, "bytes": 1833104}, {"id": 2, "name": "5_(1-2)", "s": "5_1", "d": "5_2", "instructions": 55859, "bytes": 4420603}], "transmission": [{"module": "5_0", "message_in": "M.USER.APP.5", "message_out": "5_(0-1)"}, {"module": "5_1", "message_in": "5_(0-1)", "message_out": "5_(1-2)"}, {"module": "5_2", "message_in": "5_(1-2)"}]}, {"id": 6, "name": 6, "module": [{"id": 0, "name": "6_0", "RAM": 2, "type": "MODULE"}, {"id": 1, "name": "6_1", "RAM": 5, "type": "MODULE"}], "message": [{"id": 0, "name": "M.USER.APP.6", "s": "None", "d": "6_0", "instructions": 25405, "bytes": 1799114}, {"id": 1, "name": "6_(0-1)", "s": "6_0", "d": "6_1", "instructions": 54768, "bytes": 2369157}], "transmission": [{"module": "6_0", "message_in": "M.USER.APP.6", "message_out": "6_(0-1)"}, {"module": "6_1", "message_in": "6_(0-1)"}]}, {"id": 7, "name": 7, "module": [{"id": 0, "name": "7_0", "RAM": 4, "type": "MODULE"}, {"id": 1, "name": "7_1", "RAM": 4, "type": "MODULE"}, {"id": 2, "name": "7_2", "RAM": 3, "type": "MODULE"}], "message": [{"id": 0, "name": "M.USER.APP.7", "s": "None", "d": "7_0", "instructions": 28333, "bytes": 2378605}, {"id": 1, "name": "7_(0-1)", "s": "7_0", "d": "7_1", "instructions": 27506, "bytes": 3772114}, {"id": 2, "name": "7_(1-2)", "s": "7_1", "d": "7_2", "instructions": 56210, "bytes": 4346813}], "transmission": [{"module": "7_0", "message_in": "M.USER.APP.7", "message_out": "7_(0-1)"}, {"module": "7_1", "message_in": "7_(0-1)", "message_out": "7_(1-2)"}, {"module": "7_2", "message_in": "7_(1-2)"}]}, {"id": 8, "name": 8, "module": [{"id": 0, "name": "8_0", "RAM": 3, "type": "MODULE"}, {"id": 1, "name": "8_1", "RAM": 1, "type": "MODULE"}, {"id": 2, "name": "8_2", "RAM": 2, "type": "MODULE"}, {"id": 3, "name": "8_3", "RAM": 1, "type": "MODULE"}], "message": [{"id": 0, "name": "M.USER.APP.8", "s": "None", "d": "8_0", "instructions": 46565, "bytes": 4181661}, {"id": 1, "name": "8_(0-1)", "s": "8_0", "d": "8_1", "instructions": 20866, "bytes": 2549587}, {"id": 2, "name": "8_(1-2)", "s": "8_1", "d": "8_2", "instructions": 41584, "bytes": 4111627}, {"id": 3, "name": "8_(2-3)", "s": "8_2", "d": "8_3", "instructions": 47561, "bytes": 3739579}], "transmission": [{"module": "8_0", "message_in": "M.USER.APP.8", "message_out": "8_(0-1)"}, {"module": "8_1", "message_in": "8_(0-1)", "message_out": "8_(1-2)"}, {"module": "8_2", "message_in": "8_(1-2)", "message_out": "8_(2-3)"}, {"module": "8_3", "message_in": "8_(2-3)"}]}, {"id": 9, "name": 9, "module": [{"id": 0, "name": "9_0", "RAM": 4, "type": "MODULE"}, {"id": 1, "name": "9_1", "RAM": 2, "type": "MODULE"}], "message": [{"id": 0, "name": "M.USER.APP.9", "s": "None", "d": "9_0", "instructions": 31581, "bytes": 2687344}, {"id": 1, "name": "9_(0-1)", "s": "9_0", "d": "9_1", "instructions": 51396, "bytes": 3671872}], "transmission": [{"module": "9_0", "message_in": "M.USER.APP.9", "message_out": "9_(0-1)"}, {"module": "9_1", "message_in": "9_(0-1)"}]}]