{"sources": [{"app": 0, "message": "M.USER.APP.0", "id_resource": 8, "lambda": 645}, {"app": 1, "message": "M.USER.APP.1", "id_resource": 7, "lambda": 368}, {"app": 2, "message": "M.USER.APP.2", "id_resource": 8, "lambda": 546}, {"app": 2, "message": "M.USER.APP.2", "id_resource": 9, "lambda": 204}, {"app": 3, "message": "M.USER.APP.3", "id_resource": 9, "lambda": 845}, {"app": 4, "message": "M.USER.APP.4", "id_resource": 7, "lambda": 254}, {"app": 5, "message": "M.USER.APP.5", "id_resource": 9, "lambda": 696}, {"app": 6, "message": "M.USER.APP.6", "id_resource": 9, "lambda": 387}, {"app": 7, "message": "M.USER.APP.7", "id_resource": 9, "lambda": 773}, {"app": 8, "message": "M.USER.APP.8", "id_resource": 9, "lambda": 356}, {"app": 9, "message": "M.USER.APP.9", "id_resource": 9, "lambda": 537}]}